geodatahub/__init__.py
geodatahub/auth.py
geodatahub/connection.py
geodatahub/exceptions.py
geodatahub/models.py
geodatahub-2020.3.post1.dist-info/LICENSE.txt
geodatahub-2020.3.post1.dist-info/METADATA
geodatahub-2020.3.post1.dist-info/WHEEL
geodatahub-2020.3.post1.dist-info/top_level.txt
geodatahub-2020.3.post1.dist-info/RECORD
